{
   "$schema": "vscode://schemas/color-theme",
   "name": "SVA - Light Default Highlights",
   "tokenColors": [{
         "name":"visibility: public, memory, ..",
         "scope":"storage.type.modifier.keyword.cellscript",
         "settings":{
            "foreground":"#2a9b0e",
            "fontStyle":"underline"
         }
      },
      {
         "name":"external visibility",
         "scope":"storage.type.modifier.keyword.extendedscope.cellscript",
         "settings":{
            "foreground":"#d65353",
            "fontStyle":"underline"
         }
      },
      {
         "name":"emit, new, delete",
         "scope":"keyword.control.cellscript",
         "settings":{
            "foreground":"#c200b2ad",
            "fontStyle":"bold"
         }
      },
      {
         "name":"function contract",
         "scope":"entity.name.function.cellscript",
         "settings":{
            //"foreground":"#fae674d7",
            "fontStyle":""
         }
      },
      {
         "name":"transaction vars (inconclusive)",
         "scope":"variable.language.transaction.cellscript",
         "settings":{
            "foreground":"#e4a13c",
            "fontStyle":"bold underline"
         }
      },
      {
         "name":"transaction vars (sec)",
         "scope":"variable.language.transaction.security.cellscript",
         "settings":{
            "foreground":"#e05959",
            "fontStyle":"bold underline"
         }
      },
      {
         "name":"transaction function (sec)",
         "scope":"support.function.transaction.security.cellscript",
         "settings":{
            "foreground":"#e05959",
            "fontStyle":"bold underline"
         }
      },
      {
         "name":"transaction function (safe)",
         "scope":"support.function.transaction.cellscript",
         "settings":{
            "foreground":"#e4a13c",
            "fontStyle":"bold"
         }
      },
      {
         "name":"assembly",
         "scope":"keyword.control.assembly.cellscript",
         "settings":{
            "foreground":"#e05959",
            "fontStyle":"bold underline"
         }
      },
      {
         "name":"unchecked",
         "scope":"keyword.control.unchecked.cellscript",
         "settings":{
            "foreground":"#e05959",
            "fontStyle":"bold underline"
         }
      },
      {
         "name":"let",
         "scope":"keyword.control.let.cellscript",
         "settings":{
            "foreground":"#e05959",
            "fontStyle":"bold underline"
         }
      },
      {
         "name":"todos and dev notes",
         "scope":"keyword.comment.todo.cellscript",
         "settings":{
            "foreground":"#e05959",
            "fontStyle":"bold underline italic"
         }
      },
      {
         "name":"assert/require",
         "scope":"keyword.control.exceptions.cellscript",
         "settings":{
            "foreground":"#2a9b0e",
            "fontStyle":"underline"
         }
      },
      {
         "name":"modifier function",
         "scope":"entity.name.modifier.cellscript",
         "settings":{
            "foreground":"#2a9b0e",
         }
      },
      {
         "name":"this",
         "scope":"variable.language.this.cellscript",
         "settings":{
            "fontStyle":"bold underline"
         }
      },
      {
         "name":"super",
         "scope":"variable.language.super.cellscript",
         "settings":{
            "fontStyle":"bold underline"
         }
      },
      {
         "name":"selfdestruct",
         "scope":"keyword.control.contract.cellscript",
         "settings":{
            "foreground":"#e05959",
            "fontStyle":"bold underline"
         }
      },
      {
         "name":"builtin math",
         "scope":"support.function.math.cellscript",
         "settings":{
            "fontStyle":"bold italic"
         }
      },
      {
         "name":"arithm",
         "scope":"keyword.operator.arithmetic.cellscript",
         "settings":{
            "foreground":"#2654d2",
            "fontStyle":"bold"
         }
      },
      {
         "name":"assign",
         "scope":"keyword.operator.assignment.cellscript",
         "settings":{
            "foreground":"#6bac04",
            "fontStyle":"bold"
         }
      },
      {
         "name":"logic",
         "scope":"keyword.operator.logic.cellscript",
         "settings":{
            "foreground":"#e09c43",
            "fontStyle":"bold"
         }
      },
      {
         "name":"using",
         "scope":"keyword.control.using.cellscript",
         "settings":{
            "fontStyle":"underline"
         }
      },
      {
         "name":"import",
         "scope":"keyword.control.import.cellscript",
         "settings":{
            //"foreground":"#fc8a56a6",
            "fontStyle":"bold italic"
         }
      },
      {
         "name":"pragma",
         "scope":"keyword.control.pragma.cellscript",
         "settings":{
            //"foreground":"#fc8a56a6",
            "fontStyle":"bold italic"
         }
      },
      {
         "name":"underscore placeholder",
         "scope":"constant.other.underscore.cellscript",
         "settings":{
            "fontStyle":"bold underline"
         }
      },
      {
         "name":"const time",
         "scope":"constant.language.time.cellscript",
         "settings":{
            "foreground":"#d68661ea",
            "fontStyle":"underline"
         }
      },
      {
         "name":"const currency",
         "scope":"constant.language.currency.cellscript",
         "settings":{
            "foreground":"#d68661ea",
            "fontStyle":"underline"
         }
      },
      {
         "name":"contract",
         "scope":"storage.type.contract.cellscript",
         "settings":{
            "fontStyle":"italic"
         }
      },
      {
         "name":"is",
         "scope":"storage.modifier.is.cellscript",
         "settings":{
            "fontStyle":"italic"
         }
      },
      {
         "name":"interface",
         "scope":"storage.type.interface.cellscript",
         "settings":{
            "fontStyle":"italic"
         }
      },
      {
         "name":"package",
         "scope":"storage.type.package.cellscript",
         "settings":{
            "fontStyle":"italic"
         }
      },
      {
         "name":"struct",
         "scope":"storage.type.struct.cellscript",
         "settings":{
            "fontStyle":"italic"
         }
      },
      {
         "name":"event",
         "scope":"storage.type.event.cellscript",
         "settings":{
            "fontStyle":"italic"
         }
      },
      {
         "name":"constructor",
         "scope":"storage.type.constructor.cellscript",
         "settings":{
            "foreground":"#268BD2",
            "fontStyle":"bold underline"
         }
      },
      {
         "name":"receive",
         "scope":"storage.type.function.receive.cellscript",
         "settings":{
            "foreground":"#268BD2",
            "fontStyle":"underline bold"
         }
      },
      {
         "name":"enum",
         "scope":"entity.name.type.enum.cellscript",
         "settings":{
            "fontStyle":"italic"
         }
      },
      {
         "name":"function",
         "scope":"storage.type.function.cellscript",
         "settings":{
            "fontStyle":"italic"
         }
      },
      {
         "name":"visibility: public, memory, ..",
         "scope":"constant.language.ucase.cellscript",
         "settings":{
            "foreground":"#6098c0",
            "fontStyle":"italic"
         }
      },
      {
         "name":"modifier",
         "scope":"storage.type.modifier.cellscript",
         "settings":{
            "fontStyle":"italic"
         }
      },
      {
         "name":"natspec param",
         "scope":"storage.type.title.natspec",
         "settings":{
            "foreground":"#8c8c8c"
         }
      },
      {
         "name":"natspec param",
         "scope":"storage.type.author.natspec",
         "settings":{
            "foreground":"#8c8c8c"
         }
      },
      {
         "name":"natspec param",
         "scope":"storage.type.dev.natspec",
         "settings":{
            "foreground":"#8c8c8c"
         }
      },
      {
         "name":"natspec param",
         "scope":"storage.type.return.natspec",
         "settings":{
            "foreground":"#8c8c8c"
         }
      },
      {
         "name":"natspec param",
         "scope":"storage.type.param.natspec",
         "settings":{
            "foreground":"#8c8c8c"
         }
      },
      {
         "name":"natspec value",
         "scope":"variable.other.natspec",
         "settings":{
            "foreground":"#535353"
         }
      },
      {
         "name":"block",
         "scope":"punctuation.block.cellscript",
         "settings":{
            "foreground":"#0000008f",
            "fontStyle": "bold"
         }
      }
   ]
}